nicedjango/models.py
nicedjango/__init__.py
nicedjango/_compat.py
nicedjango/graph/utils.py
nicedjango/graph/__init__.py
nicedjango/graph/node.py
nicedjango/graph/loader.py
nicedjango/graph/relation.py
nicedjango/graph/dumper.py
nicedjango/graph/graph.py
nicedjango/management/__init__.py
nicedjango/management/commands/load_graph.py
nicedjango/management/commands/__init__.py
nicedjango/management/commands/dump_graph.py
nicedjango/utils/fields.py
nicedjango/utils/models.py
nicedjango/utils/__init__.py
nicedjango/utils/label.py
nicedjango/utils/compact_csv.py
nicedjango/utils/bulk.py
nicedjango/utils/queries.py
nicedjango/utils/py/args.py
nicedjango/utils/py/__init__.py
nicedjango/utils/py/operator.py
nicedjango/utils/py/collections.py
nicedjango/utils/py/iter.py
nicedjango/utils/py/chunk.py
nicedjango/utils/py/string.py
nicedjango/utils/py/file.py
nicedjango/serializers/compact_base.py
nicedjango/serializers/compact_yaml.py
nicedjango/serializers/__init__.py
nicedjango/serializers/compact_csv.py
nicedjango/serializers/compact_python.py
nicedjango-1.2.0.dist-info/top_level.txt
nicedjango-1.2.0.dist-info/DESCRIPTION.rst
nicedjango-1.2.0.dist-info/RECORD
nicedjango-1.2.0.dist-info/METADATA
nicedjango-1.2.0.dist-info/metadata.json
nicedjango-1.2.0.dist-info/WHEEL
